tests/__init__.py
tests/test_collection.py
tests/test_database.py
tests/test_integration.py
tests/test_query.py
notsql-1.0.0.dist-info/METADATA
notsql-1.0.0.dist-info/WHEEL
notsql-1.0.0.dist-info/entry_points.txt
notsql-1.0.0.dist-info/top_level.txt
notsql-1.0.0.dist-info/RECORD
